authelio_sdk/__init__.py
authelio_sdk/client.py
authelio_sdk/client_base.py
authelio_sdk/client_group.py
authelio_sdk/client_user.py
authelio_sdk/config.py
authelio_sdk/models/__init__.py
authelio_sdk/models/group.py
authelio_sdk/models/token.py
authelio_sdk/models/user.py
authelio_sdk_tests/integration/__init__.py
authelio_sdk_tests/integration/conftest.py
authelio_sdk_tests/integration/fixtures/__init__.py
authelio_sdk_tests/integration/fixtures/group.py
authelio_sdk_tests/integration/fixtures/sdk_client.py
authelio_sdk_tests/integration/fixtures/user.py
authelio_sdk_tests/integration/tests/__init__.py
authelio_sdk_tests/integration/tests/group/__init__.py
authelio_sdk_tests/integration/tests/group/test_create.py
authelio_sdk_tests/integration/tests/group/test_delete.py
authelio_sdk_tests/integration/tests/group/test_filter.py
authelio_sdk_tests/integration/tests/group/test_get.py
authelio_sdk_tests/integration/tests/group/test_update.py
authelio_sdk_tests/integration/tests/group/test_users.py
authelio_sdk_tests/integration/tests/permission/__init__.py
authelio_sdk_tests/integration/tests/permission/test_get.py
authelio_sdk_tests/integration/tests/token/__init__.py
authelio_sdk_tests/integration/tests/token/test_challenge.py
authelio_sdk_tests/integration/tests/token/test_create.py
authelio_sdk_tests/integration/tests/token/test_refresh.py
authelio_sdk_tests/integration/tests/token/test_validate.py
authelio_sdk_tests/integration/tests/user/__init__.py
authelio_sdk_tests/integration/tests/user/test_create.py
authelio_sdk_tests/integration/tests/user/test_delete.py
authelio_sdk_tests/integration/tests/user/test_disable.py
authelio_sdk_tests/integration/tests/user/test_enable.py
authelio_sdk_tests/integration/tests/user/test_filter.py
authelio_sdk_tests/integration/tests/user/test_get.py
authelio_sdk_tests/integration/tests/user/test_update.py
authelio_sdk-3.1.1.dist-info/LICENSE
authelio_sdk-3.1.1.dist-info/METADATA
authelio_sdk-3.1.1.dist-info/WHEEL
authelio_sdk-3.1.1.dist-info/top_level.txt
authelio_sdk-3.1.1.dist-info/RECORD
