Metadata-Version: 2.1
Name: authelio-sdk
Version: 3.1.1
Summary: Authelio Python SDK
Home-page: https://github.com/Biomapas/AuthelioPythonSDK.git
Author: Gediminas Kazlauskas
Author-email: gediminas.kazlauskas@biomapas.com
License: Apache License 2.0
Keywords: Authelio Python SDK
Platform: UNKNOWN
Classifier: Programming Language :: Python :: 3
Classifier: Operating System :: OS Independent
Requires-Dist: b-lambda-layer-common (<5.0.0,>=4.2.2)
Requires-Dist: urllib3 (<2.0.0,>=1.26.0)
